aio_easycodefpy/__init__.py
aio_easycodefpy/connector.py
aio_easycodefpy/easycodefpy.py
aio_easycodefpy/message.py
aio_easycodefpy/properties.py
aio_easycodefpy/util.py
tests/__init__.py
tests/helper.py
tests/test_connector.py
tests/test_easycodefpy.py
tests/test_util.py
aio_easycodefpy-1.0.0.dist-info/LICENSE
aio_easycodefpy-1.0.0.dist-info/METADATA
aio_easycodefpy-1.0.0.dist-info/WHEEL
aio_easycodefpy-1.0.0.dist-info/top_level.txt
aio_easycodefpy-1.0.0.dist-info/RECORD
